File_Format.py
__init__.py
fileformatter-0.0.1.dist-info/METADATA
fileformatter-0.0.1.dist-info/WHEEL
fileformatter-0.0.1.dist-info/entry_points.txt
fileformatter-0.0.1.dist-info/licenses/LICENSE
fileformatter-0.0.1.dist-info/RECORD
