Metadata-Version: 2.1
Name: FileFormatter
Version: 0.0.1
Summary: A program that clears long text files
Author-Email: Kodjo Messie <kodjomessie@gmail.com>
Classifier: Programming Language :: Python :: 3
Classifier: License :: OSI Approved :: MIT License
Classifier: Operating System :: OS Independent
Requires-Python: >=3.8
